tech1200/__init__.py
tech1200/module.py
tech1200-0.0.3.dist-info/METADATA
tech1200-0.0.3.dist-info/WHEEL
tech1200-0.0.3.dist-info/top_level.txt
tech1200-0.0.3.dist-info/RECORD
