Metadata-Version: 2.1
Name: tech1200
Version: 0.0.3
Summary: A module with course info, current time, and planetary data
Home-page: https://github.com/yourusername/mymodule
Author: Your Name
Author-email: your.email@example.com
Classifier: Programming Language :: Python :: 3
Classifier: License :: OSI Approved :: MIT License
Classifier: Operating System :: OS Independent
Requires-Python: >=3.6
Requires-Dist: pandas (>=1.0.0)
